Workbook
Name Aporte: Simulador!$E$23
Name Patrimonio: Simulador!$E$26
Name Qty_anos: Simulador!$E$24
Name Rendimento_Carteira: Simulador!$E$18
Name Salario: Simulador!$E$17
Name Sugestao_Investimento: Simulador!$E$19
Name Taxa_mensal: Simulador!$E$25

Sheet Simulador
B16: CONFIGURAÇÕES
B17: Salário | E17: 5000
B18: Rendimento da Carteira | E18: 0.006
B19: Sugestão de Investimento 30% | E19: =E17*30% -> 1500
B22: INVESTIMENTO MENSAL
B23: Quanto eu devo investir por mês? | E23: 1260
B24: Por quantos anos devo investir? | E24: 5
B25: Taxa de rendimento mensal? | E25: 0.01079
B26: Patrimônio Acumulado? | E26: =FV(Taxa_mensal,Qty_anos*12,Aporte*-1) -> 105558.91
B27: Dividendos Mensais? | E27: =Patrimonio*Rendimento_Carteira -> 633.35347
B30: CENÁRIOS
C31: qty anos | D31: Patrimônio | E31: Dividendo
B32: Investido em anos | C32: 2 | D32: =FV($E$25,$C32*12,Aporte*-1) -> 34306.81 | E32: =D32*Rendimento_Carteira -> 205.84086
B33: Investido em anos | C33: 5 | D33: =FV($E$25,$C33*12,Aporte*-1) -> 105558.91 | E33: =D33*Rendimento_Carteira -> 633.35347
B34: Investido em anos | C34: 10 | D34: =FV($E$25,$C34*12,Aporte*-1) -> 306538.11 | E34: =D34*Rendimento_Carteira -> 1839.2286
B35: Investido em anos | C35: 20 | D35: =FV($E$25,$C35*12,Aporte*-1) -> 1417750 | E35: =D35*Rendimento_Carteira -> 8506.4999
B36: Investido em anos | C36: 30 | D36: =FV($E$25,$C36*12,Aporte*-1) -> 5445933.8 | E36: =D36*Rendimento_Carteira -> 32675.603
B39: PERFIL | E39: MODERADO
B40: Valor a ser investido por mês | E40: =Aporte -> 1260
B42: TIPOS DE FII | D42: Percentual Sugerido | E42: Valores
B43: PAPEL | D43: =VLOOKUP($E$39&"-"&B43,Dados_Procv!$A:$D,4,FALSE) -> 0.32 | E43: =$E$40*D43 -> 403.2
B44: TIJOLO | D44: =VLOOKUP($E$39&"-"&B44,Dados_Procv!$A:$D,4,FALSE) -> 0.35 | E44: =$E$40*D44 -> 441
B45: HIBRÍDOS | D45: =VLOOKUP($E$39&"-"&B45,Dados_Procv!$A:$D,4,FALSE) -> 0.08 | E45: =$E$40*D45 -> 100.8
B46: FOF'S | D46: =VLOOKUP($E$39&"-"&B46,Dados_Procv!$A:$D,4,FALSE) -> 0.05 | E46: =$E$40*D46 -> 63
B47: DESENVOLVIMENTO | D47: =VLOOKUP($E$39&"-"&B47,Dados_Procv!$A:$D,4,FALSE) -> 0.1 | E47: =$E$40*D47 -> 126
B48: HOTELARIAS | D48: =VLOOKUP($E$39&"-"&B48,Dados_Procv!$A:$D,4,FALSE) -> 0.1 | E48: =$E$40*D48 -> 126
E49: =SUM(E43:E48) -> 1260

Sheet Dados_Procv
A1: CHAVE COMPOSTA | B1: PERFIS | C1: TIPOS DE FII | D1: %
A2: =B2&"-"&C2 -> CONSERVADOR-PAPEL | B2: CONSERVADOR | C2: PAPEL | D2: 0.3
A3: =B3&"-"&C3 -> CONSERVADOR-TIJOLO | B3: CONSERVADOR | C3: TIJOLO | D3: 0.5
A4: =B4&"-"&C4 -> CONSERVADOR-HIBRÍDOS | B4: CONSERVADOR | C4: HIBRÍDOS | D4: 0.1
A5: =B5&"-"&C5 -> CONSERVADOR-FOF'S | B5: CONSERVADOR | C5: FOF'S | D5: 0.1
A6: =B6&"-"&C6 -> CONSERVADOR-DESENVOLVIMENTO | B6: CONSERVADOR | C6: DESENVOLVIMENTO | D6: 0
A7: =B7&"-"&C7 -> CONSERVADOR-HOTELARIAS | B7: CONSERVADOR | C7: HOTELARIAS | D7: 0
A8: =B8&"-"&C8 -> MODERADO-PAPEL | B8: MODERADO | C8: PAPEL | D8: 0.32
A9: =B9&"-"&C9 -> MODERADO-TIJOLO | B9: MODERADO | C9: TIJOLO | D9: 0.35
A10: =B10&"-"&C10 -> MODERADO-HIBRÍDOS | B10: MODERADO | C10: HIBRÍDOS | D10: 0.08
A11: =B11&"-"&C11 -> MODERADO-FOF'S | B11: MODERADO | C11: FOF'S | D11: 0.05
A12: =B12&"-"&C12 -> MODERADO-DESENVOLVIMENTO | B12: MODERADO | C12: DESENVOLVIMENTO | D12: 0.1
A13: =B13&"-"&C13 -> MODERADO-HOTELARIAS | B13: MODERADO | C13: HOTELARIAS | D13: 0.1
... A19: =B19&"-"&C19 -> AGRESSIVO-HOTELARIAS | B19: AGRESSIVO | C19: HOTELARIAS | D19: 0.1

Sheet Orientações do Projeto
A1: Entendendo o Desafio
A3: Agora é a sua hora de praticar, aprender fazendo e construir no Excel uma ferramenta que simula investimentos em fundos imobiliários, do aporte de cada mês aos dividendos que ele rende.
A5: Nas Aulas, o Expert Felipe Aguiar, o Felipão, explica o básico de fundos imobiliários e monta a ferramenta com você, passo a passo. Não existe base de dados para baixar: todo valor e todo percentual que ele usa aparece na tela.
A7: O Que Criar
A9: Uma planilha com cara de aplicativo, que responda às cinco perguntas de negócio levantadas antes de abrir o Excel:
A11: Quanto investir por mês;
A12: Por quantos anos;
A13: Qual a taxa de rendimento mensal;
A14: Quanto de patrimônio vai acumular;
A15: Quanto vai receber de dividendos por mês.
A17: Ela também projeta o patrimônio em cenários de 2 a 30 anos e divide o aporte entre seis tipos de fundo imobiliário, conforme o perfil de investidor escolhido numa lista.
A19: Como Fazer
... A83: Bons estudos e bom projeto 🚀
